AUTHOR.txt
CHANGES.txt
LICENSE.txt
buildout.cfg
setup.py
bootstrap/bootstrap.py
src/falkolab/__init__.py
src/falkolab.resource.egg-info/PKG-INFO
src/falkolab.resource.egg-info/SOURCES.txt
src/falkolab.resource.egg-info/dependency_links.txt
src/falkolab.resource.egg-info/namespace_packages.txt
src/falkolab.resource.egg-info/not-zip-safe
src/falkolab.resource.egg-info/requires.txt
src/falkolab.resource.egg-info/top_level.txt
src/falkolab/resource/README.txt
src/falkolab/resource/__init__.py
src/falkolab/resource/adapters.py
src/falkolab/resource/configure.zcml
src/falkolab/resource/ftesting.zcml
src/falkolab/resource/interfaces.py
src/falkolab/resource/meta.zcml
src/falkolab/resource/resourcetypes.py
src/falkolab/resource/resourcetypes.zcml
src/falkolab/resource/testing.py
src/falkolab/resource/tests.py
src/falkolab/resource/util.py
src/falkolab/resource/zcml.py
src/falkolab/resource/package/__init__.py
src/falkolab/resource/package/configure.zcml
src/falkolab/resource/package/meta.zcml
src/falkolab/resource/package/package.txt
src/falkolab/resource/package/resourcepackage.py
src/falkolab/resource/package/zcml.py
src/falkolab/resource/zrt/__init__.py
src/falkolab/resource/zrt/configure.zcml
src/falkolab/resource/zrt/zrtresourcetype.py