Metadata-Version: 1.0
Name: falkolab.resource
Version: 1.0.3
Summary: Alternative extensible resource implementation.
Home-page: http://falkolab.ru
Author: Andrey Tkachenko
Author-email: falko.lab@gmail.com
License: ZPL 2.1
Platform: UNKNOWN
Classifier: Development Status :: 5 - Production/Stable
Classifier: Framework :: Zope3
Classifier: Environment :: Web Environment
Classifier: License :: OSI Approved :: Zope Public License
Classifier: Programming Language :: Python
Classifier: Natural Language :: English
Classifier: Operating System :: OS Independent
Classifier: Intended Audience :: Developers
Classifier: Topic :: Software Development :: User Interfaces
